ecuth/__init__.py
ecuth/base.py
ecuth/challenge.py
ecuth/digest.py
ecuth/error.py
ecuth/session.py
ecuth/ext/__init__.py
ecuth/ext/eth.py
ecuth/ext/pgp.py
ecuth/filter/eip712.py
ecuth/filter/hoba.py
ecuth/filter/pgp.py
ecuth-0.4.4.dist-info/LICENSE.txt
ecuth-0.4.4.dist-info/METADATA
ecuth-0.4.4.dist-info/WHEEL
ecuth-0.4.4.dist-info/top_level.txt
ecuth-0.4.4.dist-info/RECORD
