Metadata-Version: 2.1
Name: ecuth
Version: 0.4.4
Summary: Public-key signature based authentication and authorization backend
Home-page: https://gitlab.com/nolash/euth
Author: Louis Holbrook
Author-email: dev@holbrook.no
License: GPL3
Keywords: ethereum
Platform: UNKNOWN
Classifier: Programming Language :: Python :: 3
Classifier: Operating System :: OS Independent
Classifier: Development Status :: 3 - Alpha
Classifier: Environment :: No Input/Output (Daemon)
Classifier: Intended Audience :: Developers
Classifier: License :: OSI Approved :: GNU General Public License v3 or later (GPLv3+)
Classifier: Topic :: Internet
Requires-Python: >=3.6
Requires-Dist: pysha3 (==1.0.2)
Requires-Dist: eth-keys (==0.3.3)
Requires-Dist: python-gnupg (==0.4.6)
Requires-Dist: confini (==0.3.5)
Provides-Extra: eip712
Requires-Dist: eip712-structs (==1.1.0) ; extra == 'eip712'
Provides-Extra: hoba
Requires-Dist: http-hoba-auth (==0.2.0) ; extra == 'hoba'
